datasette_paste/__init__.py
datasette_paste/static/papaparse-5-4-1.min.js
datasette_paste/templates/paste_create_table.html
datasette_paste-0.1a5.dist-info/LICENSE
datasette_paste-0.1a5.dist-info/METADATA
datasette_paste-0.1a5.dist-info/WHEEL
datasette_paste-0.1a5.dist-info/entry_points.txt
datasette_paste-0.1a5.dist-info/top_level.txt
datasette_paste-0.1a5.dist-info/RECORD
