Metadata-Version: 2.1
Name: datasette-paste
Version: 0.1a5
Summary: Paste data to create tables in Datasette
Author: Simon Willison
License: Apache-2.0
Project-URL: Homepage, https://github.com/datasette/datasette-paste
Project-URL: Changelog, https://github.com/datasette/datasette-paste/releases
Project-URL: Issues, https://github.com/datasette/datasette-paste/issues
Project-URL: CI, https://github.com/datasette/datasette-paste/actions
Classifier: Framework :: Datasette
Classifier: License :: OSI Approved :: Apache Software License
Requires-Python: >=3.8
License-File: LICENSE
Requires-Dist: datasette >=1.0a13
Provides-Extra: test
Requires-Dist: pytest ; extra == 'test'
Requires-Dist: pytest-asyncio ; extra == 'test'
